{
  "name": "Nell Reynolds",
  "age": 26,
  "address": {
    "street": "Aguudu Manor",
    "city": "Vopwiuso",
    "state": "MS",
    "zip": "54365"
  },
  "contact": {
    "phone": "(511) 664-1869",
    "servicePhone": "800635511"
  },
  "birthday": "1994-05-12T01:23:24.293Z",
  "ip": "59.214.31.183",
  "foo": "bar",
  "profile": {
    "about": "Ko zepuzap gar wajufle ig aruun ezgefja ikru nofu asafu ge cakowen dezev kafod. Hagevu gise vu kewfuvcom hec fazotef gazsu feluat nogduos dotfozpiz dom cig efaso temikna fol hoekbem. Bazicuv zeahril juwne vabtopla si ovzufceh ja walvuspes feja kaju saevoowu rumzez feledad zeeviwi jorfus we va. Acvosiza racaawo jocuwofu kujrogit batga lugiz zu ap juaw fakiifi loh how cutumar. Pon gab ag wunegor docacu cobag jec sulujjo dur po okwuop netoiha fe uzigod ceoklez jot acori.",
    "bio": "Zi bate faksama va firfe mot nas na vu riama od zimzeuv gigdapa tockib lurib. Gigjof zoopounu ger hogiker si musbugu gi huh esesi rez luz firzamja ud justelfuc roja kobov. Kuzzom sob fusocnu vu ewoore elsa mucuis ruzfig towlurbo ajzi zoh owvubnu to ago buodlat. Pejbenlud jehup panwujif ro misasak zov na capo ezwebdet hejic tinepiso tavroz lerug uja zomegfuj casoguto. Pewrudab unka rocpur poeserap ejoam naw umoag ta he jisdujem beraziw ocda sowwog gezlanos fiska zisu zuves ni. Hobi ituni tefpe ahaekaoli lilfafpid vul kovidu jofawru sitarris taz ji tuwis ru taf nok adu iriz po."
  },
  "apiKey": "2cb64a2ead3d3c56484d06cb66028b3382e9da57e84a85882ac1464ce3cd5d6e",
  "currency": {
    "code": "AUD",
    "name": "Australia Dollar"
  }
}